{"ongoing_trials": {}, "hyperparameters": {"space": [{"class_name": "Choice", "config": {"name": "lstm_type", "default": "simple", "conditions": [], "values": ["simple", "bidirectional"], "ordered": false}}, {"class_name": "Int", "config": {"name": "units", "default": null, "conditions": [], "min_value": 32, "max_value": 128, "step": 16, "sampling": "linear"}}, {"class_name": "Float", "config": {"name": "dropout_rate1", "default": 0.1, "conditions": [], "min_value": 0.1, "max_value": 0.5, "step": 0.1, "sampling": "linear"}}, {"class_name": "Int", "config": {"name": "units2", "default": null, "conditions": [], "min_value": 16, "max_value": 64, "step": 8, "sampling": "linear"}}, {"class_name": "Float", "config": {"name": "dropout_rate2", "default": 0.1, "conditions": [], "min_value": 0.1, "max_value": 0.5, "step": 0.1, "sampling": "linear"}}, {"class_name": "Boolean", "config": {"name": "include_dense", "default": false, "conditions": []}}, {"class_name": "Float", "config": {"name": "learning_rate", "default": 0.0001, "conditions": [], "min_value": 0.0001, "max_value": 0.01, "step": null, "sampling": "log"}}, {"class_name": "Int", "config": {"name": "dense_units", "default": null, "conditions": [], "min_value": 8, "max_value": 32, "step": 8, "sampling": "linear"}}], "values": {"lstm_type": "simple", "units": 32, "dropout_rate1": 0.1, "units2": 16, "dropout_rate2": 0.1, "include_dense": false, "learning_rate": 0.0001, "dense_units": 8}}, "start_order": ["0", "1", "2", "3", "4"], "end_order": ["0", "1", "2", "3", "4"], "run_times": {"0": 1, "1": 1, "2": 1, "3": 1, "4": 1}, "retry_queue": [], "seed": 7323, "seed_state": 7362, "tried_so_far": ["c95a8b2451d6e5b1b023dab03694b8ec", "8b4dccc268eaf3ba4016a00eae0f707c", "718d7e09cb43bab68529353d3df2c660", "4849909dfc77757f323ba0a58ea6cbe8", "2cbc2f5f2d00c24e71b12bcb63ffa500"], "id_to_hash": {"0": "c95a8b2451d6e5b1b023dab03694b8ec", "1": "718d7e09cb43bab68529353d3df2c660", "2": "8b4dccc268eaf3ba4016a00eae0f707c", "3": "2cbc2f5f2d00c24e71b12bcb63ffa500", "4": "4849909dfc77757f323ba0a58ea6cbe8"}, "display": {"search_start": "2025-04-10T10:11:13.650025", "trial_start": {"0": "2025-04-10T10:11:13.650025", "1": "2025-04-10T10:11:29.216247", "2": "2025-04-10T10:11:47.400167", "3": "2025-04-10T10:12:00.601934", "4": "2025-04-10T10:12:10.967145"}, "trial_number": {"0": 1, "1": 2, "2": 3, "3": 4, "4": 5}}}